LICENSE
README.md
setup.py
src/fingerprint_enhancer/__init__.py
src/fingerprint_enhancer/fingerprint_image_enhancer.py
src/fingerprint_enhancer.egg-info/PKG-INFO
src/fingerprint_enhancer.egg-info/SOURCES.txt
src/fingerprint_enhancer.egg-info/dependency_links.txt
src/fingerprint_enhancer.egg-info/requires.txt
src/fingerprint_enhancer.egg-info/top_level.txt