Metadata-Version: 2.1
Name: fingerprint_enhancer
Version: 0.0.14
Summary: enhance fingerprint images
Home-page: https://github.com/Utkarsh-Deshmukh/Fingerprint-Enhancement-Python
Download-URL: https://github.com/Utkarsh-Deshmukh/Fingerprint-Enhancement-Python/archive/develop.zip
Author: utkarsh-deshmukh
Author-email: utkarsh.deshmukh@gmail.com
License: MIT
Keywords: Fingerprint Image Enhancement
Classifier: Programming Language :: Python :: 3
Classifier: License :: OSI Approved :: MIT License
Classifier: Operating System :: OS Independent
License-File: LICENSE
Requires-Dist: numpy
Requires-Dist: opencv-python
Requires-Dist: scipy
